python_docx_replace/__init__.py
python_docx_replace/block_handler.py
python_docx_replace/exceptions.py
python_docx_replace/key_changer.py
python_docx_replace/paragraph.py
python_docx_replace-0.4.4.dist-info/LICENSE
python_docx_replace-0.4.4.dist-info/METADATA
python_docx_replace-0.4.4.dist-info/WHEEL
python_docx_replace-0.4.4.dist-info/top_level.txt
python_docx_replace-0.4.4.dist-info/RECORD
