Metadata-Version: 2.1
Name: python-docx-replace
Version: 0.4.4
Summary: Replace words and remove blocks inside a Word document without losing format
Home-page: https://github.com/ivanbicalho/python-docx-replace
Author: Ivan Bicalho
Author-email: ivanribeirob@gmail.com
Classifier: Programming Language :: Python :: 3
Classifier: License :: OSI Approved :: MIT License
Classifier: Operating System :: OS Independent
License-File: LICENSE
